ironfonts/__init__.py
ironfonts/batch_naming.py
ironfonts/cli_functions.py
ironfonts/custom_functions.py
ironfonts/repaste_underrange.py
ironfonts/reserve_ligatures.py
ironfonts/select_set.py
ironfonts/sets.py
ironfonts-0.8.dist-info/METADATA
ironfonts-0.8.dist-info/WHEEL
ironfonts-0.8.dist-info/licenses/LICENSE
ironfonts-0.8.dist-info/RECORD
