Metadata-Version: 2.1
Name: ironfonts
Version: 0.8
Summary: Modules for aiding and scripting the use of FontForge, built on the the 'fontforge' python-package.
Author-email: Isaac Erb <isaac.n.erb@gmail.com>
License-File: LICENSE
Keywords: font,fontforge,typography
Classifier: Development Status :: 3 - Alpha
Classifier: Intended Audience :: Developers
Classifier: License :: OSI Approved :: GNU General Public License v3 (GPLv3)
Classifier: Programming Language :: Python :: 3.6
Classifier: Programming Language :: Python :: 3.7
Classifier: Programming Language :: Python :: 3.8
Classifier: Programming Language :: Python :: 3.9
Classifier: Programming Language :: Python :: 3.10
Classifier: Topic :: Software Development
Requires-Python: >=3.6
